mxpyserializer/__init__.py
mxpyserializer/__main__.py
mxpyserializer/abi_serializer.py
mxpyserializer/basic_type.py
mxpyserializer/data_models.py
mxpyserializer/errors.py
mxpyserializer-0.3.2.dist-info/LICENSE
mxpyserializer-0.3.2.dist-info/METADATA
mxpyserializer-0.3.2.dist-info/WHEEL
mxpyserializer-0.3.2.dist-info/entry_points.txt
mxpyserializer-0.3.2.dist-info/top_level.txt
mxpyserializer-0.3.2.dist-info/RECORD
