Metadata-Version: 2.1
Name: mxpyserializer
Version: 0.3.2
Summary: Python package that serialize and deserialize MultiversX data format by using ABI definitions
Author: Etienne Wallet
Project-URL: Homepage, https://github.com/Catenscia/MxPySerializer
Keywords: elrond,multiversx,smart-contract,ABI,data,serialize
Classifier: Programming Language :: Python :: 3
Classifier: License :: OSI Approved :: MIT License
Classifier: Operating System :: OS Independent
Requires-Python: >=3.10
License-File: LICENSE
Requires-Dist: multiversx-sdk-core ~=0.7.3
